tinycrate/__init__.py
tinycrate/jsonld_context.py
tinycrate/py.typed
tinycrate/tinycrate.py
tinycrate-0.1.3.dist-info/METADATA
tinycrate-0.1.3.dist-info/WHEEL
tinycrate-0.1.3.dist-info/RECORD
