Metadata-Version: 2.4
Name: tinycrate
Version: 0.1.3
Summary: A lightweight RO-Crate library
Author-email: Mike Lynch <m.lynch@sydney.edu.au>, Peter Sefton <p.sefton@uq.edu.au>
Requires-Python: >=3.11
Requires-Dist: requests>=2.32.3
Requires-Dist: types-requests>=2.32.0.20250602
